README.txt
setup.py
asciiimage/__init__.py
asciiimage/asciiimage.py
asciiimage/asciivideo.py
asciiimage/manipulate.py
asciiimage/sprite.py
asciiimage.egg-info/PKG-INFO
asciiimage.egg-info/SOURCES.txt
asciiimage.egg-info/dependency_links.txt
asciiimage.egg-info/top_level.txt
asciiimage.egg-info/zip-safe