Metadata-Version: 1.0
Name: asciiimage
Version: 0.0
Summary: Work with images made of ASCII text.
Home-page: https://github.com/GreyAlien502/ASCIIImage
Author: GreyAlien502
Author-email: greyalien502@gmail.com
License: MIT
Platform: UNKNOWN
